pyflashtext/__init__.py
pyflashtext/keyword.py
pyflashtext-2.7.1.dist-info/LICENSE
pyflashtext-2.7.1.dist-info/METADATA
pyflashtext-2.7.1.dist-info/WHEEL
pyflashtext-2.7.1.dist-info/top_level.txt
pyflashtext-2.7.1.dist-info/RECORD
