Metadata-Version: 2.1
Name: pyflashtext
Version: 2.7.1
Summary: Extract/Replaces keywords in sentences.
Home-page: http://github.com/francbartoli/pyflashtext
Author: Francesco Bartoli
Author-email: xbartolone@gmail.com
License: UNKNOWN
Platform: any
Classifier: Programming Language :: Python
Classifier: Programming Language :: Python :: 3.6
Classifier: Programming Language :: Python :: 3.7
Classifier: Programming Language :: Python :: 3.8
Classifier: Programming Language :: Python :: 3.9
Classifier: Operating System :: OS Independent
Classifier: Intended Audience :: Developers
Classifier: License :: OSI Approved :: MIT License
